<?xml version="1.0" encoding="UTF-8"?>
<ti:work xmlns:ti="http://chs.harvard.edu/xmlns/cts" urn="urn:cts:latinLit:phi1017.phi006"
  groupUrn="urn:cts:latinLit:phi1017" xml:lang="lat">
  <ti:title xml:lang="eng">Oedipus</ti:title>
  <ti:title xml:lang="fre">Œdipe</ti:title>
  <ti:edition urn="urn:cts:latinLit:phi1017.phi006.perseus-lat2"
    workUrn="urn:cts:latinLit:phi1017.phi006">
    <ti:label xml:lang="eng">Oedipus</ti:label>
    <ti:description xml:lang="eng">Seneca, Lucius Annaeus, ca. 4 B.C.-65 A.D, creator; Peiper,
      Rudolf, 1834-1898, editor; Richter, Gustav, 1838-1904, editor</ti:description>
  </ti:edition>
</ti:work>
